pilmoji_fixed/__init__.py
pilmoji_fixed/classes.py
pilmoji_fixed/constants.py
pilmoji_fixed/helpers.py
pilmoji_fixed/aio/__init__.py
pilmoji_fixed/aio/core.py
pilmoji_fixed/aio/http.py
pilmoji_fixed/sync/__init__.py
pilmoji_fixed/sync/core.py
pilmoji_fixed/sync/http.py
pilmoji_fixed-1.3.2.dist-info/METADATA
pilmoji_fixed-1.3.2.dist-info/WHEEL
pilmoji_fixed-1.3.2.dist-info/top_level.txt
pilmoji_fixed-1.3.2.dist-info/RECORD
