Metadata-Version: 2.1
Name: pilmoji-fixed
Version: 1.3.2
Summary: Pilmoji is a fast and reliable emoji renderer for PIL.
Home-page: https://github.com/stunnerr/pilmoji
Author: jay3332 (fix by stunnerr)
License: UNKNOWN
Platform: UNKNOWN
Classifier: Programming Language :: Python :: 3
Classifier: License :: OSI Approved :: MIT License
Classifier: Operating System :: OS Independent
Requires-Dist: requests
Requires-Dist: aiohttp
Requires-Dist: pillow
Requires-Dist: emoji
